swarmpyfac/__init__.py
swarmpyfac/fac.py
swarmpyfac/utils.py
swarmpyfac-0.2.1.dist-info/LICENSE
swarmpyfac-0.2.1.dist-info/METADATA
swarmpyfac-0.2.1.dist-info/WHEEL
swarmpyfac-0.2.1.dist-info/top_level.txt
swarmpyfac-0.2.1.dist-info/RECORD
