Metadata-Version: 2.1
Name: swarmpyfac
Version: 0.2.1
Summary: Calculate Field Aligned Currents based on swarm data, mainly through the ViRES python interface viresclient. Some utilities for these kinds of scientific calculations are also provided.
Home-page: https://github.com/Swarm-DISC/SwarmPyFAC
Author: Ask Neve Gamby
Author-email: aknvg@space.dtu.dk
License: None
Keywords: FAC,Field Aligned Currents,magnetic field
Platform: UNKNOWN
Classifier: Development Status :: 2 - Pre-Alpha
Classifier: Intended Audience :: Science/Research
Classifier: Programming Language :: Python
Classifier: Programming Language :: Python :: 3
Classifier: Programming Language :: Python :: 3.4
Classifier: Programming Language :: Python :: 3.5
Classifier: Programming Language :: Python :: 3.6
Classifier: Programming Language :: Python :: 3.7
Classifier: Topic :: Scientific/Engineering :: Physics
Requires-Dist: cdflib
Requires-Dist: matplotlib
Requires-Dist: numpy
Requires-Dist: scipy
Requires-Dist: viresclient
